odoo8_addon_mrp_repair_report_customer_lang-8.0.1.0.0-py2.7-nspkg.pth
odoo_addons/mrp_repair_report_customer_lang/__openerp__.py
odoo_addons/mrp_repair_report_customer_lang/mrp_repair_report.xml
odoo_addons/mrp_repair_report_customer_lang/__init__.py
odoo_addons/mrp_repair_report_customer_lang/README.rst
odoo_addons/mrp_repair_report_customer_lang/views/report_mrp_repair_order.xml
odoo_addons/mrp_repair_report_customer_lang/static/description/icon.png
odoo8_addon_mrp_repair_report_customer_lang-8.0.1.0.0.dist-info/top_level.txt
odoo8_addon_mrp_repair_report_customer_lang-8.0.1.0.0.dist-info/WHEEL
odoo8_addon_mrp_repair_report_customer_lang-8.0.1.0.0.dist-info/RECORD
odoo8_addon_mrp_repair_report_customer_lang-8.0.1.0.0.dist-info/metadata.json
odoo8_addon_mrp_repair_report_customer_lang-8.0.1.0.0.dist-info/DESCRIPTION.rst
odoo8_addon_mrp_repair_report_customer_lang-8.0.1.0.0.dist-info/METADATA
odoo8_addon_mrp_repair_report_customer_lang-8.0.1.0.0.dist-info/namespace_packages.txt
